{ "columns":15,
 "image":"S2093.png",
 "imageheight":320,
 "imagewidth":240,
 "margin":0,
 "name":"S2093",
 "spacing":0,
 "terrains":[
        {
         "name":"\u8352\u5730",
         "properties":[
                {
                 "name":"default",
                 "type":"bool",
                 "value":true
                }],
         "tile":-1
        }, 
        {
         "name":"\u8981\u585e",
         "tile":-1
        }, 
        {
         "name":"\u5ca9\u6d46",
         "tile":-1
        }, 
        {
         "name":"\u6811",
         "tile":-1
        }],
 "tilecount":300,
 "tiledversion":"1.4.1",
 "tileheight":16,
 "tiles":[
        {
         "id":12,
         "terrain":[2, 2, 2, 2]
        }, 
        {
         "id":13,
         "terrain":[2, 2, 2, 2]
        }, 
        {
         "id":14,
         "terrain":[2, 2, 2, 2]
        }, 
        {
         "id":27,
         "terrain":[2, 2, 2, 2]
        }, 
        {
         "id":28,
         "terrain":[2, 2, 2, 2]
        }, 
        {
         "id":29,
         "terrain":[2, 2, 2, 2]
        }, 
        {
         "id":42,
         "terrain":[2, 2, 2, 2]
        }, 
        {
         "id":43,
         "terrain":[2, 2, 2, 2]
        }, 
        {
         "id":53,
         "terrain":[1, 1, 1, 1]
        }, 
        {
         "id":54,
         "terrain":[1, 1, 1, 1]
        }, 
        {
         "id":68,
         "terrain":[1, 1, 1, 1]
        }, 
        {
         "id":69,
         "terrain":[1, 1, 1, 1]
        }, 
        {
         "id":80,
         "terrain":[3, 3, 3, 3]
        }, 
        {
         "id":81,
         "terrain":[3, 3, 3, 3]
        }, 
        {
         "id":82,
         "terrain":[3, 3, 3, 3]
        }, 
        {
         "id":83,
         "terrain":[2, 2, 2, 2]
        }, 
        {
         "id":84,
         "terrain":[2, 2, 2, 2]
        }, 
        {
         "id":87,
         "terrain":[3, 3, 3, 3]
        }, 
        {
         "id":88,
         "terrain":[3, 3, 3, 3]
        }, 
        {
         "id":89,
         "terrain":[3, 3, 3, 3]
        }, 
        {
         "id":95,
         "terrain":[3, 3, 3, 3]
        }, 
        {
         "id":96,
         "terrain":[3, 3, 3, 3]
        }, 
        {
         "id":97,
         "terrain":[3, 3, 3, 3]
        }, 
        {
         "id":98,
         "terrain":[2, 2, 2, 2]
        }, 
        {
         "id":99,
         "terrain":[2, 2, 2, 2]
        }, 
        {
         "id":102,
         "terrain":[3, 3, 3, 3]
        }, 
        {
         "id":103,
         "terrain":[3, 3, 3, 3]
        }, 
        {
         "id":104,
         "terrain":[3, 3, 3, 3]
        }, 
        {
         "id":110,
         "terrain":[3, 3, 3, 3]
        }, 
        {
         "id":111,
         "terrain":[3, 3, 3, 3]
        }, 
        {
         "id":113,
         "terrain":[2, 2, 2, 2]
        }, 
        {
         "id":114,
         "terrain":[2, 2, 2, 2]
        }, 
        {
         "id":119,
         "terrain":[3, 3, 3, 3]
        }, 
        {
         "id":125,
         "terrain":[1, 1, 1, 1]
        }, 
        {
         "id":126,
         "terrain":[1, 1, 1, 1]
        }, 
        {
         "id":128,
         "terrain":[2, 2, 2, 2]
        }, 
        {
         "id":129,
         "terrain":[2, 2, 2, 2]
        }, 
        {
         "id":140,
         "terrain":[1, 1, 1, 1]
        }, 
        {
         "id":141,
         "terrain":[1, 1, 1, 1]
        }, 
        {
         "id":143,
         "terrain":[2, 2, 2, 2]
        }, 
        {
         "id":153,
         "terrain":[3, 3, 3, 3]
        }, 
        {
         "id":154,
         "terrain":[3, 3, 3, 3]
        }, 
        {
         "id":167,
         "terrain":[3, 3, 3, 3]
        }, 
        {
         "id":168,
         "terrain":[3, 3, 3, 3]
        }, 
        {
         "id":169,
         "terrain":[3, 3, 3, 3]
        }, 
        {
         "id":182,
         "terrain":[3, 3, 3, 3]
        }, 
        {
         "id":183,
         "terrain":[3, 3, 3, 3]
        }, 
        {
         "id":200,
         "terrain":[2, 2, 2, 2]
        }, 
        {
         "id":201,
         "terrain":[2, 2, 2, 2]
        }, 
        {
         "id":215,
         "terrain":[2, 2, 2, 2]
        }, 
        {
         "id":216,
         "terrain":[2, 2, 2, 2]
        }, 
        {
         "id":230,
         "terrain":[2, 2, 2, 2]
        }, 
        {
         "id":231,
         "terrain":[2, 2, 2, 2]
        }, 
        {
         "id":235,
         "terrain":[3, 3, 3, 3]
        }, 
        {
         "id":236,
         "terrain":[3, 3, 3, 3]
        }, 
        {
         "id":245,
         "terrain":[2, 2, 2, 2]
        }, 
        {
         "id":246,
         "terrain":[2, 2, 2, 2]
        }, 
        {
         "id":250,
         "terrain":[3, 3, 3, 3]
        }, 
        {
         "id":251,
         "terrain":[3, 3, 3, 3]
        }, 
        {
         "id":270,
         "terrain":[3, 3, 3, 3]
        }, 
        {
         "id":271,
         "terrain":[3, 3, 3, 3]
        }, 
        {
         "id":275,
         "terrain":[1, 1, 1, 1]
        }, 
        {
         "id":276,
         "terrain":[1, 1, 1, 1]
        }, 
        {
         "id":283,
         "terrain":[2, 2, 2, 2]
        }, 
        {
         "id":284,
         "terrain":[2, 2, 2, 2]
        }, 
        {
         "id":285,
         "terrain":[3, 3, 3, 3]
        }, 
        {
         "id":286,
         "terrain":[3, 3, 3, 3]
        }, 
        {
         "id":290,
         "terrain":[1, 1, 1, 1]
        }, 
        {
         "id":291,
         "terrain":[1, 1, 1, 1]
        }, 
        {
         "id":298,
         "terrain":[2, 2, 2, 2]
        }, 
        {
         "id":299,
         "terrain":[2, 2, 2, 2]
        }],
 "tilewidth":16,
 "type":"tileset",
 "version":1.4
}