{ "columns":15,
 "image":"S4021.png",
 "imageheight":320,
 "imagewidth":240,
 "margin":0,
 "name":"S4021",
 "spacing":0,
 "terrains":[
        {
         "name":"\u5e73\u5730",
         "properties":[
                {
                 "name":"default",
                 "type":"bool",
                 "value":true
                }],
         "tile":-1
        }, 
        {
         "name":"\u68ee\u6797",
         "tile":-1
        }, 
        {
         "name":"\u5899\u58c1",
         "tile":-1
        }, 
        {
         "name":"\u95ed\u6751",
         "tile":-1
        }, 
        {
         "name":"\u5efa\u7b51",
         "tile":-1
        }],
 "tilecount":300,
 "tiledversion":"1.4.1",
 "tileheight":16,
 "tiles":[
        {
         "id":3,
         "terrain":[4, 4, 4, 4]
        }, 
        {
         "id":4,
         "terrain":[4, 4, 4, 4]
        }, 
        {
         "id":18,
         "terrain":[4, 4, 4, 4]
        }, 
        {
         "id":19,
         "terrain":[4, 4, 4, 4]
        }, 
        {
         "id":33,
         "terrain":[3, 3, 3, 3]
        }, 
        {
         "id":34,
         "terrain":[4, 4, 4, 4]
        }, 
        {
         "id":55,
         "terrain":[4, 4, 4, 4]
        }, 
        {
         "id":56,
         "terrain":[4, 4, 4, 4]
        }, 
        {
         "id":57,
         "terrain":[4, 4, 4, 4]
        }, 
        {
         "id":70,
         "terrain":[4, 4, 4, 4]
        }, 
        {
         "id":71,
         "terrain":[3, 3, 3, 3]
        }, 
        {
         "id":72,
         "terrain":[4, 4, 4, 4]
        }, 
        {
         "id":78,
         "terrain":[4, 4, 4, 4]
        }, 
        {
         "id":79,
         "terrain":[4, 4, 4, 4]
        }, 
        {
         "id":93,
         "terrain":[4, 4, 4, 4]
        }, 
        {
         "id":94,
         "terrain":[4, 4, 4, 4]
        }, 
        {
         "id":108,
         "terrain":[3, 3, 3, 3]
        }, 
        {
         "id":109,
         "terrain":[4, 4, 4, 4]
        }, 
        {
         "id":150,
         "terrain":[1, 1, 1, 1]
        }, 
        {
         "id":151,
         "terrain":[1, 1, 1, 1]
        }, 
        {
         "id":160,
         "terrain":[4, 4, 4, 4]
        }, 
        {
         "id":161,
         "terrain":[4, 4, 4, 4]
        }, 
        {
         "id":164,
         "terrain":[1, 1, 1, 1]
        }, 
        {
         "id":165,
         "terrain":[1, 1, 1, 1]
        }, 
        {
         "id":166,
         "terrain":[1, 1, 1, 1]
        }, 
        {
         "id":167,
         "terrain":[1, 1, 1, 1]
        }, 
        {
         "id":175,
         "terrain":[4, 4, 4, 4]
        }, 
        {
         "id":176,
         "terrain":[4, 4, 4, 4]
        }, 
        {
         "id":179,
         "terrain":[1, 1, 1, 1]
        }, 
        {
         "id":181,
         "terrain":[1, 1, 1, 1]
        }, 
        {
         "id":190,
         "terrain":[4, 4, 4, 4]
        }, 
        {
         "id":191,
         "terrain":[3, 3, 3, 3]
        }, 
        {
         "id":235,
         "terrain":[1, 1, 1, 1]
        }, 
        {
         "id":236,
         "terrain":[1, 1, 1, 1]
        }, 
        {
         "id":238,
         "terrain":[2, 2, 2, 2]
        }, 
        {
         "id":239,
         "terrain":[2, 2, 2, 2]
        }, 
        {
         "id":250,
         "terrain":[1, 1, 1, 1]
        }, 
        {
         "id":251,
         "terrain":[1, 1, 1, 1]
        }, 
        {
         "id":252,
         "terrain":[1, 1, 1, 1]
        }, 
        {
         "id":253,
         "terrain":[2, 2, 2, 2]
        }, 
        {
         "id":254,
         "terrain":[2, 2, 2, 2]
        }, 
        {
         "id":255,
         "terrain":[2, 2, 2, 2]
        }, 
        {
         "id":256,
         "terrain":[2, 2, 2, 2]
        }, 
        {
         "id":257,
         "terrain":[2, 2, 2, 2]
        }, 
        {
         "id":262,
         "terrain":[2, 2, 2, 2]
        }, 
        {
         "id":263,
         "terrain":[2, 2, 2, 2]
        }, 
        {
         "id":264,
         "terrain":[2, 2, 2, 2]
        }, 
        {
         "id":265,
         "terrain":[2, 2, 2, 2]
        }, 
        {
         "id":266,
         "terrain":[2, 2, 2, 2]
        }, 
        {
         "id":267,
         "terrain":[2, 2, 2, 2]
        }, 
        {
         "id":268,
         "terrain":[2, 2, 2, 2]
        }, 
        {
         "id":269,
         "terrain":[2, 2, 2, 2]
        }, 
        {
         "id":270,
         "terrain":[2, 2, 2, 2]
        }, 
        {
         "id":271,
         "terrain":[2, 2, 2, 2]
        }, 
        {
         "id":272,
         "terrain":[2, 2, 2, 2]
        }, 
        {
         "id":277,
         "terrain":[2, 2, 2, 2]
        }, 
        {
         "id":278,
         "terrain":[2, 2, 2, 2]
        }, 
        {
         "id":279,
         "terrain":[2, 2, 2, 2]
        }, 
        {
         "id":280,
         "terrain":[2, 2, 2, 2]
        }, 
        {
         "id":281,
         "terrain":[2, 2, 2, 2]
        }, 
        {
         "id":282,
         "terrain":[2, 2, 2, 2]
        }, 
        {
         "id":283,
         "terrain":[2, 2, 2, 2]
        }, 
        {
         "id":284,
         "terrain":[2, 2, 2, 2]
        }, 
        {
         "id":285,
         "terrain":[2, 2, 2, 2]
        }, 
        {
         "id":286,
         "terrain":[2, 2, 2, 2]
        }, 
        {
         "id":287,
         "terrain":[2, 2, 2, 2]
        }, 
        {
         "id":292,
         "terrain":[2, 2, 2, 2]
        }, 
        {
         "id":293,
         "terrain":[2, 2, 2, 2]
        }, 
        {
         "id":294,
         "terrain":[2, 2, 2, 2]
        }, 
        {
         "id":295,
         "terrain":[2, 2, 2, 2]
        }, 
        {
         "id":296,
         "terrain":[2, 2, 2, 2]
        }, 
        {
         "id":297,
         "terrain":[2, 2, 2, 2]
        }, 
        {
         "id":298,
         "terrain":[2, 2, 2, 2]
        }, 
        {
         "id":299,
         "terrain":[2, 2, 2, 2]
        }],
 "tilewidth":16,
 "type":"tileset",
 "version":1.4
}