{ "columns":15,
 "image":"S4093.png",
 "imageheight":320,
 "imagewidth":240,
 "margin":0,
 "name":"S4093",
 "spacing":0,
 "terrains":[
        {
         "name":"\u5e73\u5730",
         "properties":[
                {
                 "name":"default",
                 "type":"bool",
                 "value":true
                }],
         "tile":11
        }, 
        {
         "name":"\u60ac\u5d16",
         "tile":103
        }, 
        {
         "name":"\u5899\u58c1",
         "tile":225
        }, 
        {
         "name":"\u68ee\u6797",
         "tile":14
        }],
 "tilecount":300,
 "tiledversion":"1.4.2",
 "tileheight":16,
 "tiles":[
        {
         "id":0,
         "terrain":[3, 3, 3, 3]
        }, 
        {
         "id":14,
         "terrain":[3, 3, 3, 3]
        }, 
        {
         "id":15,
         "terrain":[3, 3, 3, 3]
        }, 
        {
         "id":29,
         "terrain":[3, 3, 3, 3]
        }, 
        {
         "id":30,
         "terrain":[3, 3, 3, 3]
        }, 
        {
         "id":77,
         "terrain":[1, 1, 1, 1]
        }, 
        {
         "id":79,
         "terrain":[1, 1, 1, 1]
        }, 
        {
         "id":82,
         "terrain":[1, 1, 1, 1]
        }, 
        {
         "id":84,
         "terrain":[1, 1, 1, 1]
        }, 
        {
         "id":87,
         "terrain":[1, 1, 1, 1]
        }, 
        {
         "id":92,
         "terrain":[1, 1, 1, 1]
        }, 
        {
         "id":93,
         "terrain":[1, 1, 1, 1]
        }, 
        {
         "id":94,
         "terrain":[1, 1, 1, 1]
        }, 
        {
         "id":97,
         "terrain":[1, 1, 1, 1]
        }, 
        {
         "id":98,
         "terrain":[1, 1, 1, 1]
        }, 
        {
         "id":99,
         "terrain":[1, 1, 1, 1]
        }, 
        {
         "id":102,
         "terrain":[1, 1, 1, 1]
        }, 
        {
         "id":103,
         "terrain":[1, 1, 1, 1]
        }, 
        {
         "id":104,
         "terrain":[1, 1, 1, 1]
        }, 
        {
         "id":152,
         "terrain":[1, 1, 1, 1]
        }, 
        {
         "id":154,
         "terrain":[1, 1, 1, 1]
        }, 
        {
         "id":157,
         "terrain":[1, 1, 1, 1]
        }, 
        {
         "id":159,
         "terrain":[1, 1, 1, 1]
        }, 
        {
         "id":162,
         "terrain":[1, 1, 1, 1]
        }, 
        {
         "id":167,
         "terrain":[1, 1, 1, 1]
        }, 
        {
         "id":168,
         "terrain":[1, 1, 1, 1]
        }, 
        {
         "id":169,
         "terrain":[1, 1, 1, 1]
        }, 
        {
         "id":172,
         "terrain":[1, 1, 1, 1]
        }, 
        {
         "id":173,
         "terrain":[1, 1, 1, 1]
        }, 
        {
         "id":174,
         "terrain":[1, 1, 1, 1]
        }, 
        {
         "id":177,
         "terrain":[1, 1, 1, 1]
        }, 
        {
         "id":178,
         "terrain":[1, 1, 1, 1]
        }, 
        {
         "id":179,
         "terrain":[1, 1, 1, 1]
        }, 
        {
         "id":225,
         "terrain":[2, 2, 2, 2]
        }, 
        {
         "id":226,
         "terrain":[2, 2, 2, 2]
        }, 
        {
         "id":227,
         "terrain":[1, 1, 1, 1]
        }, 
        {
         "id":229,
         "terrain":[1, 1, 1, 1]
        }, 
        {
         "id":232,
         "terrain":[1, 1, 1, 1]
        }, 
        {
         "id":233,
         "terrain":[1, 1, 1, 1]
        }, 
        {
         "id":234,
         "terrain":[1, 1, 1, 1]
        }, 
        {
         "id":235,
         "terrain":[1, 1, 1, 1]
        }, 
        {
         "id":240,
         "terrain":[2, 2, 2, 2]
        }, 
        {
         "id":241,
         "terrain":[2, 2, 2, 2]
        }, 
        {
         "id":242,
         "terrain":[1, 1, 1, 1]
        }, 
        {
         "id":243,
         "terrain":[1, 1, 1, 1]
        }, 
        {
         "id":244,
         "terrain":[1, 1, 1, 1]
        }, 
        {
         "id":247,
         "terrain":[1, 1, 1, 1]
        }, 
        {
         "id":248,
         "terrain":[1, 1, 1, 1]
        }, 
        {
         "id":249,
         "terrain":[1, 1, 1, 1]
        }, 
        {
         "id":255,
         "terrain":[3, 3, 3, 3]
        }, 
        {
         "id":269,
         "terrain":[3, 3, 3, 3]
        }, 
        {
         "id":270,
         "terrain":[3, 3, 3, 3]
        }, 
        {
         "id":284,
         "terrain":[3, 3, 3, 3]
        }, 
        {
         "id":285,
         "terrain":[3, 3, 3, 3]
        }, 
        {
         "id":286,
         "terrain":[3, 3, 3, 3]
        }, 
        {
         "id":291,
         "terrain":[3, 3, 3, 3]
        }, 
        {
         "id":292,
         "terrain":[3, 3, 3, 3]
        }, 
        {
         "id":298,
         "terrain":[3, 3, 3, 3]
        }, 
        {
         "id":299,
         "terrain":[3, 3, 3, 3]
        }],
 "tilewidth":16,
 "type":"tileset",
 "version":1.4
}